Metadata-Version: 2.1
Name: baseMEOW
Version: 1.0.0
Summary: Encode and decode information as meows
Home-page: https://github.com/driazati/baseMEOW
Author: driazati
Author-email: email@example.com
License: UNKNOWN
Platform: UNKNOWN
Classifier: Programming Language :: Python :: 3
Classifier: License :: OSI Approved :: MIT License
Classifier: Operating System :: OS Independent
Requires-Python: >=3.6
